project/verithon-main/unified_simd_and_reconfigurable/sram_32b_w2048.v
// Created by prof. Mingu Kang @VVIP Lab in UCSD ECE department
// Please do not spread this code without permission 
module sram_32b_w2048 (CLK, D, Q, CEN, WEN, A);

  input  CLK;
  input  WEN;
  input  CEN;
  input  [31:0] D;
  input  [10:0] A;
  output [31:0] Q;
  parameter num = 2048;

  reg [31:0] memory [num-1:0];
  reg [10:0] add_q;
  assign Q = memory[add_q];

  always @ (posedge CLK) begin

   if (!CEN && WEN) // read 
      add_q <= A;
   if (!CEN && !WEN) // write
      memory[A] <= D; 

  end

endmodule

// Created by prof. Mingu Kang @VVIP Lab in UCSD ECE department
// Please do not spread this code without permission 
module sram_128b_w2048 (CLK, D, Q, CEN, WEN, A);

  input  CLK;
  input  WEN;
  input  CEN;
  input  [127:0] D;
  input  [10:0] A;
  output [127:0] Q;
  parameter num = 2048;

  reg [127:0] memory [num-1:0];
  reg [10:0] add_q;
  assign Q = memory[add_q];

  always @ (posedge CLK) begin

   if (!CEN && WEN) // read 
      add_q <= A;
   if (!CEN && !WEN) // write
      memory[A] <= D; 

  end

endmodule

hw7/wk7/hw1/verilog/sram_tb.v
// Created by prof. Mingu Kang @VVIP Lab in UCSD ECE department
// Please do not spread this code without permission 

`timescale 1 ns/1 ps

module sram_tb;


`define NULL 0

reg CLK = 0;
reg [10:0]  A = 0;
reg [31:0] D_tmp = 0;
reg CEN_EXT = 0;
reg CEN_Q ;
reg WEN_EXT = 1;
reg WEN_Q ;
wire [31:0] Q;

integer x_file, x_scan_file ; // file_handler
integer captured_data; 
integer t, b, i, error;
reg [31:0] D_2D [63:0];

parameter run_cycle = 64;
parameter col = 0;

sram_32b_w2048 sram_instance (
	.CLK(CLK), 
	.CEN(CEN_Q), 
	.WEN(WEN_Q),
        .A(A), 
        .D(D_tmp), 
        .Q(Q));


initial begin 

  $dumpfile("sram_tb.vcd");
  $dumpvars(0,sram_tb);

  x_file = $fopen("activation.txt", "r");

  // Following three lines are to remove the first three comment lines of the file
  x_scan_file = $fscanf(x_file,"%s", captured_data);
  x_scan_file = $fscanf(x_file,"%s", captured_data);
  x_scan_file = $fscanf(x_file,"%s", captured_data);


  #20 CLK = 1'b1;  
 
  #20 CLK = 1'b0;   WEN_EXT = 0;

  #20 CLK = 1'b1; 

  for (t=0; t<run_cycle-1; t=t+1) begin  

    #20 CLK = 1'b0;

    A = A + 1;
    for (b = 31; b >=0; b = b-1) begin
     x_scan_file = $fscanf(x_file,"%1b", D_tmp[b]);
    end
    D_2D[t] = D_tmp;
    $display("%2d-th written data is %h", t, D_tmp);
    
    #20 CLK = 1'b1;
     
    
  end

  #20 CLK = 1'b0;   WEN_EXT = 1; A = 0;
  #20 CLK = 1'b1; 

  #20 CLK = 1'b0;   A = A + 1; error = 0;
  #20 CLK = 1'b1;   

  for (t=0; t<run_cycle-1; t=t+1) begin  

    #20 CLK = 1'b0;   A = A + 1;
    if (D_2D[t][31:0] == Q)
        $display("%2d-th read data is %h --- Data matched", t, Q);
    else begin
        $display("%2d-th read data is %h --- Data ERROR !!!", t, Q);
        error = error+1;
    end

    #20 CLK = 1'b1;   

  end

  $display("###### Total %2d errors are detected ######", error);
  #10 $finish;


end

 always @ (posedge CLK) begin
   WEN_Q <= WEN_EXT;
   CEN_Q <= CEN_EXT;
 end

endmodule

hw7/wk7/hw1/sram_tb.vcd
$date
	Tue Nov 25 00:49:31 2025
$end
$version
	Icarus Verilog
$end
$timescale
	1ps
$end
$scope module sram_tb $end
$var wire 32 ! Q [31:0] $end
$var reg 11 " A [10:0] $end
$var reg 1 # CEN_EXT $end
$var reg 1 $ CEN_Q $end
$var reg 1 % CLK $end
$var reg 32 & D_tmp [31:0] $end
$var reg 1 ' WEN_EXT $end
$var reg 1 ( WEN_Q $end
$var integer 32 ) b [31:0] $end
$var integer 32 * captured_data [31:0] $end
$var integer 32 + error [31:0] $end
$var integer 32 , t [31:0] $end
$var integer 32 - x_file [31:0] $end
$var integer 32 . x_scan_file [31:0] $end
$scope module sram_instance $end
$var wire 11 / A [10:0] $end
$var wire 1 $ CEN $end
$var wire 1 % CLK $end
$var wire 32 0 D [31:0] $end
$var wire 32 1 Q [31:0] $end
$var wire 1 ( WEN $end
$var reg 11 2 add_q [10:0] $end
$upscope $end
$upscope $end
$enddefinitions $end
#0
$dumpvars
bx 2
bx 1
b0 0
b0 /
b1 .
b10000000000000000000000000000011 -
bx ,
bx +
b101110001011100010111000100011 *
bx )
x(
1'
b0 &
0%
x$
0#
b0 "
bx !
$end
#20000
0$
1(
1%
#40000
0'
0%
#60000
0(
b0 2
b0 ,
1%
#80000
b10000000100000001000001000000 &
b10000000100000001000001000000 0
b11111111111111111111111111111111 )
b1 "
b1 /
0%
#100000
b1 ,
1%
#120000
b100000001000000110000 &
b100000001000000110000 0
b11111111111111111111111111111111 )
b10 "
b10 /
0%
#140000
b10 ,
1%
#160000
b1000100000001000000100000 &
b1000100000001000000100000 0
b11111111111111111111111111111111 )
b11 "
b11 /
0%
#180000
b11 ,
1%
#200000
b0 &
b0 0
b11111111111111111111111111111111 )
b100 "
b100 /
0%
#220000
b100 ,
1%
#240000
b11111111111111111111111111111111 )
b101 "
b101 /
0%
#260000
b101 ,
1%
#280000
b100000000000001000001 &
b100000000000001000001 0
b11111111111111111111111111111111 )
b110 "
b110 /
0%
#300000
b110 ,
1%
#320000
b100001000100000000000001110001 &
b100001000100000000000001110001 0
b11111111111111111111111111111111 )
b111 "
b111 /
0%
#340000
b111 ,
1%
#360000
b1000010000100000000000010000000 &
b1000010000100000000000010000000 0
b11111111111111111111111111111111 )
b1000 "
b1000 /
0%
#380000
b1000 ,
1%
#400000
b1010001000100000000000001110000 &
b1010001000100000000000001110000 0
b11111111111111111111111111111111 )
b1001 "
b1001 /
0%
#420000
b1001 ,
1%
#440000
b110000000100000001000001010000 &
b110000000100000001000001010000 0
b11111111111111111111111111111111 )
b1010 "
b1010 /
0%
#460000
b1010 ,
1%
#480000
b10000000100000001000001000000 &
b10000000100000001000001000000 0
b11111111111111111111111111111111 )
b1011 "
b1011 /
0%
#500000
b1011 ,
1%
#520000
b10000000100000010000001000000 &
b10000000100000010000001000000 0
b11111111111111111111111111111111 )
b1100 "
b1100 /
0%
#540000
b1100 ,
1%
#560000
b10000000100000001000001000000 &
b10000000100000001000001000000 0
b11111111111111111111111111111111 )
b1101 "
b1101 /
0%
#580000
b1101 ,
1%
#600000
b100000010000001000000 &
b100000010000001000000 0
b11111111111111111111111111111111 )
b1110 "
b1110 /
0%
#620000
b1110 ,
1%
#640000
b11111111111111111111111111111111 )
b1111 "
b1111 /
0%
#660000
b1111 ,
1%
#680000
b10000000000000001000001010000 &
b10000000000000001000001010000 0
b11111111111111111111111111111111 )
b10000 "
b10000 /
0%
#700000
b10000 ,
1%
#720000
b1000001000000000000000010010000 &
b1000001000000000000000010010000 0
b11111111111111111111111111111111 )
b10001 "
b10001 /
0%
#740000
b10001 ,
1%
#760000
b110000000000000000000001110000 &
b110000000000000000000001110000 0
b11111111111111111111111111111111 )
b10010 "
b10010 /
0%
#780000
b10010 ,
1%
#800000
b10000000100000000000001100001 &
b10000000100000000000001100001 0
b11111111111111111111111111111111 )
b10011 "
b10011 /
0%
#820000
b10011 ,
1%
#840000
b10000000100000000000001110001 &
b10000000100000000000001110001 0
b11111111111111111111111111111111 )
b10100 "
b10100 /
0%
#860000
b10100 ,
1%
#880000
b100000000100000000000001100001 &
b100000000100000000000001100001 0
b11111111111111111111111111111111 )
b10101 "
b10101 /
0%
#900000
b10101 ,
1%
#920000
b10000000100000000000001000010 &
b10000000100000000000001000010 0
b11111111111111111111111111111111 )
b10110 "
b10110 /
0%
#940000
b10110 ,
1%
#960000
b1000100000001000000100001 &
b1000100000001000000100001 0
b11111111111111111111111111111111 )
b10111 "
b10111 /
0%
#980000
b10111 ,
1%
#1000000
b10000100100001000100010000 &
b10000100100001000100010000 0
b11111111111111111111111111111111 )
b11000 "
b11000 /
0%
#1020000
b11000 ,
1%
#1040000
b1000000100000000100000000 &
b1000000100000000100000000 0
b11111111111111111111111111111111 )
b11001 "
b11001 /
0%
#1060000
b11001 ,
1%
#1080000
b100000000 &
b100000000 0
b11111111111111111111111111111111 )
b11010 "
b11010 /
0%
#1100000
b11010 ,
1%
#1120000
b0 &
b0 0
b11111111111111111111111111111111 )
b11011 "
b11011 /
0%
#1140000
b11011 ,
1%
#1160000
b100001 &
b100001 0
b11111111111111111111111111111111 )
b11100 "
b11100 /
0%
#1180000
b11100 ,
1%
#1200000
b100000000000000010001 &
b100000000000000010001 0
b11111111111111111111111111111111 )
b11101 "
b11101 /
0%
#1220000
b11101 ,
1%
#1240000
b11111111111111111111111111111111 )
b11110 "
b11110 /
0%
#1260000
b11110 ,
1%
#1280000
b100000000000000110010 &
b100000000000000110010 0
b11111111111111111111111111111111 )
b11111 "
b11111 /
0%
#1300000
b11111 ,
1%
#1320000
b10001000100000001000001000001 &
b10001000100000001000001000001 0
b11111111111111111111111111111111 )
b100000 "
b100000 /
0%
#1340000
b100000 ,
1%
#1360000
b100010000100010001000001010001 &
b100010000100010001000001010001 0
b11111111111111111111111111111111 )
b100001 "
b100001 /
0%
#1380000
b100001 ,
1%
#1400000
b100010000100010000000001000000 &
b100010000100010000000001000000 0
b11111111111111111111111111111111 )
b100010 "
b100010 /
0%
#1420000
b100010 ,
1%
#1440000
b100000000100000000000001000000 &
b100000000100000000000001000000 0
b11111111111111111111111111111111 )
b100011 "
b100011 /
0%
#1460000
b100011 ,
1%
#1480000
b100000001000000110000 &
b100000001000000110000 0
b11111111111111111111111111111111 )
b100100 "
b100100 /
0%
#1500000
b100100 ,
1%
#1520000
b100000001000000100000 &
b100000001000000100000 0
b11111111111111111111111111111111 )
b100101 "
b100101 /
0%
#1540000
b100101 ,
1%
#1560000
b0 &
b0 0
b11111111111111111111111111111111 )
b100110 "
b100110 /
0%
#1580000
b100110 ,
1%
#1600000
b11111111111111111111111111111111 )
b100111 "
b100111 /
0%
#1620000
b100111 ,
1%
#1640000
b110001 &
b110001 0
b11111111111111111111111111111111 )
b101000 "
b101000 /
0%
#1660000
b101000 ,
1%
#1680000
b10001000100000000000001110010 &
b10001000100000000000001110010 0
b11111111111111111111111111111111 )
b101001 "
b101001 /
0%
#1700000
b101001 ,
1%
#1720000
b100001000100000001000001110000 &
b100001000100000001000001110000 0
b11111111111111111111111111111111 )
b101010 "
b101010 /
0%
#1740000
b101010 ,
1%
#1760000
b1000001000100010000000001100000 &
b1000001000100010000000001100000 0
b11111111111111111111111111111111 )
b101011 "
b101011 /
0%
#1780000
b101011 ,
1%
#1800000
b1000000000100000000000001000000 &
b1000000000100000000000001000000 0
b11111111111111111111111111111111 )
b101100 "
b101100 /
0%
#1820000
b101100 ,
1%
#1840000
b10000000100000001000001000000 &
b10000000100000001000001000000 0
b11111111111111111111111111111111 )
b101101 "
b101101 /
0%
#1860000
b101101 ,
1%
#1880000
b10000000100000010000001000000 &
b10000000100000010000001000000 0
b11111111111111111111111111111111 )
b101110 "
b101110 /
0%
#1900000
b101110 ,
1%
#1920000
b100000001000000110000 &
b100000001000000110000 0
b11111111111111111111111111111111 )
b101111 "
b101111 /
0%
#1940000
b101111 ,
1%
#1960000
b100000010000000110000 &
b100000010000000110000 0
b11111111111111111111111111111111 )
b110000 "
b110000 /
0%
#1980000
b110000 ,
1%
#2000000
b10000000100000001000001000000 &
b10000000100000001000001000000 0
b11111111111111111111111111111111 )
b110001 "
b110001 /
0%
#2020000
b110001 ,
1%
#2040000
b10000000100000001000001100000 &
b10000000100000001000001100000 0
b11111111111111111111111111111111 )
b110010 "
b110010 /
0%
#2060000
b110010 ,
1%
#2080000
b100000000100000000000001100000 &
b100000000100000000000001100000 0
b11111111111111111111111111111111 )
b110011 "
b110011 /
0%
#2100000
b110011 ,
1%
#2120000
b10000000100000000000001000000 &
b10000000100000000000001000000 0
b11111111111111111111111111111111 )
b110100 "
b110100 /
0%
#2140000
b110100 ,
1%
#2160000
b100000000000000100001 &
b100000000000000100001 0
b11111111111111111111111111111111 )
b110101 "
b110101 /
0%
#2180000
b110101 ,
1%
#2200000
b11111111111111111111111111111111 )
b110110 "
b110110 /
0%
#2220000
b110110 ,
1%
#2240000
b1000100000001000000010001 &
b1000100000001000000010001 0
b11111111111111111111111111111111 )
b110111 "
b110111 /
0%
#2260000
b110111 ,
1%
#2280000
b1000100010000000000010001 &
b1000100010000000000010001 0
b11111111111111111111111111111111 )
b111000 "
b111000 /
0%
#2300000
b111000 ,
1%
#2320000
b1000100010001000000010001 &
b1000100010001000000010001 0
b11111111111111111111111111111111 )
b111001 "
b111001 /
0%
#2340000
b111001 ,
1%
#2360000
b10000100100000000100010000 &
b10000100100000000100010000 0
b11111111111111111111111111111111 )
b111010 "
b111010 /
0%
#2380000
b111010 ,
1%
#2400000
b10010000000100000000100000000 &
b10010000000100000000100000000 0
b11111111111111111111111111111111 )
b111011 "
b111011 /
0%
#2420000
b111011 ,
1%
#2440000
b10001 &
b10001 0
b11111111111111111111111111111111 )
b111100 "
b111100 /
0%
#2460000
b111100 ,
1%
#2480000
b100001 &
b100001 0
b11111111111111111111111111111111 )
b111101 "
b111101 /
0%
#2500000
b111101 ,
1%
#2520000
b10000000000000000000000110001 &
b10000000000000000000000110001 0
b11111111111111111111111111111111 )
b111110 "
b111110 /
0%
#2540000
b111110 ,
1%
#2560000
b1000000000000000000100001 &
b1000000000000000000100001 0
b11111111111111111111111111111111 )
b111111 "
b111111 /
0%
#2580000
b111111 ,
1%
#2600000
b0 "
b0 /
1'
0%
#2620000
1(
b1000000000000000000100001 !
b1000000000000000000100001 1
1%
#2640000
b0 +
b1 "
b1 /
0%
#2660000
b10000000100000001000001000000 !
b10000000100000001000001000000 1
b1 2
b0 ,
1%
#2680000
b10 "
b10 /
0%
#2700000
b100000001000000110000 !
b100000001000000110000 1
b10 2
b1 ,
1%
#2720000
b11 "
b11 /
0%
#2740000
b1000100000001000000100000 !
b1000100000001000000100000 1
b11 2
b10 ,
1%
#2760000
b100 "
b100 /
0%
#2780000
b0 !
b0 1
b100 2
b11 ,
1%
#2800000
b101 "
b101 /
0%
#2820000
b101 2
b100 ,
1%
#2840000
b110 "
b110 /
0%
#2860000
b100000000000001000001 !
b100000000000001000001 1
b110 2
b101 ,
1%
#2880000
b111 "
b111 /
0%
#2900000
b100001000100000000000001110001 !
b100001000100000000000001110001 1
b111 2
b110 ,
1%
#2920000
b1000 "
b1000 /
0%
#2940000
b1000010000100000000000010000000 !
b1000010000100000000000010000000 1
b1000 2
b111 ,
1%
#2960000
b1001 "
b1001 /
0%
#2980000
b1010001000100000000000001110000 !
b1010001000100000000000001110000 1
b1001 2
b1000 ,
1%
#3000000
b1010 "
b1010 /
0%
#3020000
b110000000100000001000001010000 !
b110000000100000001000001010000 1
b1010 2
b1001 ,
1%
#3040000
b1011 "
b1011 /
0%
#3060000
b10000000100000001000001000000 !
b10000000100000001000001000000 1
b1011 2
b1010 ,
1%
#3080000
b1100 "
b1100 /
0%
#3100000
b10000000100000010000001000000 !
b10000000100000010000001000000 1
b1100 2
b1011 ,
1%
#3120000
b1101 "
b1101 /
0%
#3140000
b10000000100000001000001000000 !
b10000000100000001000001000000 1
b1101 2
b1100 ,
1%
#3160000
b1110 "
b1110 /
0%
#3180000
b100000010000001000000 !
b100000010000001000000 1
b1110 2
b1101 ,
1%
#3200000
b1111 "
b1111 /
0%
#3220000
b1111 2
b1110 ,
1%
#3240000
b10000 "
b10000 /
0%
#3260000
b10000000000000001000001010000 !
b10000000000000001000001010000 1
b10000 2
b1111 ,
1%
#3280000
b10001 "
b10001 /
0%
#3300000
b1000001000000000000000010010000 !
b1000001000000000000000010010000 1
b10001 2
b10000 ,
1%
#3320000
b10010 "
b10010 /
0%
#3340000
b110000000000000000000001110000 !
b110000000000000000000001110000 1
b10010 2
b10001 ,
1%
#3360000
b10011 "
b10011 /
0%
#3380000
b10000000100000000000001100001 !
b10000000100000000000001100001 1
b10011 2
b10010 ,
1%
#3400000
b10100 "
b10100 /
0%
#3420000
b10000000100000000000001110001 !
b10000000100000000000001110001 1
b10100 2
b10011 ,
1%
#3440000
b10101 "
b10101 /
0%
#3460000
b100000000100000000000001100001 !
b100000000100000000000001100001 1
b10101 2
b10100 ,
1%
#3480000
b10110 "
b10110 /
0%
#3500000
b10000000100000000000001000010 !
b10000000100000000000001000010 1
b10110 2
b10101 ,
1%
#3520000
b10111 "
b10111 /
0%
#3540000
b1000100000001000000100001 !
b1000100000001000000100001 1
b10111 2
b10110 ,
1%
#3560000
b11000 "
b11000 /
0%
#3580000
b10000100100001000100010000 !
b10000100100001000100010000 1
b11000 2
b10111 ,
1%
#3600000
b11001 "
b11001 /
0%
#3620000
b1000000100000000100000000 !
b1000000100000000100000000 1
b11001 2
b11000 ,
1%
#3640000
b11010 "
b11010 /
0%
#3660000
b100000000 !
b100000000 1
b11010 2
b11001 ,
1%
#3680000
b11011 "
b11011 /
0%
#3700000
b0 !
b0 1
b11011 2
b11010 ,
1%
#3720000
b11100 "
b11100 /
0%
#3740000
b100001 !
b100001 1
b11100 2
b11011 ,
1%
#3760000
b11101 "
b11101 /
0%
#3780000
b100000000000000010001 !
b100000000000000010001 1
b11101 2
b11100 ,
1%
#3800000
b11110 "
b11110 /
0%
#3820000
b11110 2
b11101 ,
1%
#3840000
b11111 "
b11111 /
0%
#3860000
b100000000000000110010 !
b100000000000000110010 1
b11111 2
b11110 ,
1%
#3880000
b100000 "
b100000 /
0%
#3900000
b10001000100000001000001000001 !
b10001000100000001000001000001 1
b100000 2
b11111 ,
1%
#3920000
b100001 "
b100001 /
0%
#3940000
b100010000100010001000001010001 !
b100010000100010001000001010001 1
b100001 2
b100000 ,
1%
#3960000
b100010 "
b100010 /
0%
#3980000
b100010000100010000000001000000 !
b100010000100010000000001000000 1
b100010 2
b100001 ,
1%
#4000000
b100011 "
b100011 /
0%
#4020000
b100000000100000000000001000000 !
b100000000100000000000001000000 1
b100011 2
b100010 ,
1%
#4040000
b100100 "
b100100 /
0%
#4060000
b100000001000000110000 !
b100000001000000110000 1
b100100 2
b100011 ,
1%
#4080000
b100101 "
b100101 /
0%
#4100000
b100000001000000100000 !
b100000001000000100000 1
b100101 2
b100100 ,
1%
#4120000
b100110 "
b100110 /
0%
#4140000
b0 !
b0 1
b100110 2
b100101 ,
1%
#4160000
b100111 "
b100111 /
0%
#4180000
b100111 2
b100110 ,
1%
#4200000
b101000 "
b101000 /
0%
#4220000
b110001 !
b110001 1
b101000 2
b100111 ,
1%
#4240000
b101001 "
b101001 /
0%
#4260000
b10001000100000000000001110010 !
b10001000100000000000001110010 1
b101001 2
b101000 ,
1%
#4280000
b101010 "
b101010 /
0%
#4300000
b100001000100000001000001110000 !
b100001000100000001000001110000 1
b101010 2
b101001 ,
1%
#4320000
b101011 "
b101011 /
0%
#4340000
b1000001000100010000000001100000 !
b1000001000100010000000001100000 1
b101011 2
b101010 ,
1%
#4360000
b101100 "
b101100 /
0%
#4380000
b1000000000100000000000001000000 !
b1000000000100000000000001000000 1
b101100 2
b101011 ,
1%
#4400000
b101101 "
b101101 /
0%
#4420000
b10000000100000001000001000000 !
b10000000100000001000001000000 1
b101101 2
b101100 ,
1%
#4440000
b101110 "
b101110 /
0%
#4460000
b10000000100000010000001000000 !
b10000000100000010000001000000 1
b101110 2
b101101 ,
1%
#4480000
b101111 "
b101111 /
0%
#4500000
b100000001000000110000 !
b100000001000000110000 1
b101111 2
b101110 ,
1%
#4520000
b110000 "
b110000 /
0%
#4540000
b100000010000000110000 !
b100000010000000110000 1
b110000 2
b101111 ,
1%
#4560000
b110001 "
b110001 /
0%
#4580000
b10000000100000001000001000000 !
b10000000100000001000001000000 1
b110001 2
b110000 ,
1%
#4600000
b110010 "
b110010 /
0%
#4620000
b10000000100000001000001100000 !
b10000000100000001000001100000 1
b110010 2
b110001 ,
1%
#4640000
b110011 "
b110011 /
0%
#4660000
b100000000100000000000001100000 !
b100000000100000000000001100000 1
b110011 2
b110010 ,
1%
#4680000
b110100 "
b110100 /
0%
#4700000
b10000000100000000000001000000 !
b10000000100000000000001000000 1
b110100 2
b110011 ,
1%
#4720000
b110101 "
b110101 /
0%
#4740000
b100000000000000100001 !
b100000000000000100001 1
b110101 2
b110100 ,
1%
#4760000
b110110 "
b110110 /
0%
#4780000
b110110 2
b110101 ,
1%
#4800000
b110111 "
b110111 /
0%
#4820000
b1000100000001000000010001 !
b1000100000001000000010001 1
b110111 2
b110110 ,
1%
#4840000
b111000 "
b111000 /
0%
#4860000
b1000100010000000000010001 !
b1000100010000000000010001 1
b111000 2
b110111 ,
1%
#4880000
b111001 "
b111001 /
0%
#4900000
b1000100010001000000010001 !
b1000100010001000000010001 1
b111001 2
b111000 ,
1%
#4920000
b111010 "
b111010 /
0%
#4940000
b10000100100000000100010000 !
b10000100100000000100010000 1
b111010 2
b111001 ,
1%
#4960000
b111011 "
b111011 /
0%
#4980000
b10010000000100000000100000000 !
b10010000000100000000100000000 1
b111011 2
b111010 ,
1%
#5000000
b111100 "
b111100 /
0%
#5020000
b10001 !
b10001 1
b111100 2
b111011 ,
1%
#5040000
b111101 "
b111101 /
0%
#5060000
b100001 !
b100001 1
b111101 2
b111100 ,
1%
#5080000
b111110 "
b111110 /
0%
#5100000
b10000000000000000000000110001 !
b10000000000000000000000110001 1
b111110 2
b111101 ,
1%
#5120000
b111111 "
b111111 /
0%
#5140000
b1000000000000000000100001 !
b1000000000000000000100001 1
b111111 2
b111110 ,
1%
#5160000
b1000000 "
b1000000 /
0%
#5180000
bx !
bx 1
b1000000 2
b111111 ,
1%
